README.md
setup.cfg
setup.py
psp/__init__.py
psp.egg-info/PKG-INFO
psp.egg-info/SOURCES.txt
psp.egg-info/dependency_links.txt
psp.egg-info/top_level.txt