Metadata-Version: 1.2
Name: psp
Version: 0.0.4
Summary: python color printer - minimalist color printing
Home-page: https://github.com/someburner/psp
Author: Jeff Hufford
Author-email: jeffrey92@gmail.com
License: MIT
Keywords: colorcolourterminaltextansiminimalist
Platform: UNKNOWN
Classifier: Development Status :: 2 - Pre-Alpha
Classifier: Environment :: Console
Classifier: Intended Audience :: Developers
Classifier: Operating System :: OS Independent
Classifier: Programming Language :: Python :: 3.1
Classifier: Programming Language :: Python :: 3.2
Classifier: Programming Language :: Python :: 3.3
Classifier: Programming Language :: Python :: 3.4
Classifier: Programming Language :: Python :: 3.5
Classifier: Programming Language :: Python :: 3.6
Classifier: Programming Language :: Python :: 3.7
Classifier: Topic :: Terminals
Requires-Python: >=3.1
